learna/__init__.py
learna/activations/__init__.py
learna/activations/binary_step.py
learna/activations/hyperbolic_tangent.py
learna/activations/leaky_rectified_linear_unit.py
learna/activations/linear.py
learna/activations/rectified_linear_unit.py
learna/activations/sigmoid.py
learna/activations/softmax.py
LICENSE
learna-0.1.1.dist-info/LICENSE
learna-0.1.1.dist-info/WHEEL
learna-0.1.1.dist-info/METADATA
learna-0.1.1.dist-info/RECORD
